MANIFEST.in
README.md
requirements.txt
setup.cfg
setup.py
jupyter_linter/__init__.py
jupyter_linter/jupyter_linter.py
jupyter_linter.egg-info/PKG-INFO
jupyter_linter.egg-info/SOURCES.txt
jupyter_linter.egg-info/dependency_links.txt
jupyter_linter.egg-info/entry_points.txt
jupyter_linter.egg-info/requires.txt
jupyter_linter.egg-info/top_level.txt