Metadata-Version: 1.0
Name: jupyter-linter
Version: 0.0.1
Summary: A simple linter to enforce the rules of our style guide https://goo.gl/lhK4JT.
Home-page: https://github.com/bayesimpact/jupyter-linter
Author: Stephan Gabler
Author-email: stephan@bayesimpact.org
License: The MIT License (MIT)
Keywords: linter
Platform: UNKNOWN
